fastapi_middleware_aa/__init__.py
fastapi_middleware_aa/middleware.py
fastapi_middleware_aa-0.1.0.dist-info/METADATA
fastapi_middleware_aa-0.1.0.dist-info/WHEEL
fastapi_middleware_aa-0.1.0.dist-info/top_level.txt
fastapi_middleware_aa-0.1.0.dist-info/RECORD
