Metadata-Version: 2.1
Name: fastapi-middleware-aa
Version: 0.1.0
Summary: A FastAPI middleware example
Home-page: https://github.com/yourusername/fastapi-middleware-aa
Author: Your Name
Author-email: your.email@example.com
Requires-Dist: fastapi
Requires-Dist: starlette
